{
  "scenario_id": "GNW_7.2",
  "mitigated": false,
  "mitigation": {
    "applied": false,
    "structural_frp": {
      "retrofit_map": {
        "C1-M (Pre/Lo)": "C1-M (Pre/Lo) FRP"
      },
      "coverage": {
        "whole": {
          "n_buildings": 1021,
          "n_retrofitted": 71,
          "fraction_retrofitted_by_count": 0.06953966699314397,
          "replacement_cost_php": 30636997329.0,
          "retrofitted_replacement_cost_php": 3475087383.0,
          "fraction_retrofitted_by_cost": 0.1134278057892636,
          "n_nonstructural_upgraded": 1021,
          "fraction_nonstructural_upgraded": 1.0
        },
        "makati_MC": {
          "n_buildings": 96,
          "n_retrofitted": 20,
          "fraction_retrofitted_by_count": 0.20833333333333334,
          "replacement_cost_php": 10601648074.0,
          "retrofitted_replacement_cost_php": 1866423898.0,
          "fraction_retrofitted_by_cost": 0.17605035414987122,
          "n_nonstructural_upgraded": 96,
          "fraction_nonstructural_upgraded": 1.0
        },
        "quezon_QC": {
          "n_buildings": 925,
          "n_retrofitted": 51,
          "fraction_retrofitted_by_count": 0.055135135135135134,
          "replacement_cost_php": 20035349255.0,
          "retrofitted_replacement_cost_php": 1608663485.0,
          "fraction_retrofitted_by_cost": 0.08029126243449655,
          "n_nonstructural_upgraded": 925,
          "fraction_nonstructural_upgraded": 1.0
        }
      },
      "effect": "collapse-risk reduction -> FATALITY reduction",
      "note": "Structural FRP retrofit. Reproducible coverage = C1-M (Pre/Lo) only (the one archetype with recovered R1 EDPs, collapse Sa 1.11 g -> 2.12 g). The thesis retrofitted the WHOLE ductile/non-ductile RC moment-frame stock (C1-L MCHC, C1-M HC/MC/PCLC, PTC1-M HC/MC per WVF_7_3_R1_PA.mat), so the thesis FATALITY reduction is larger than ours by construction. Not tuned."
    },
    "nonstructural": {
      "substitutions": {
        "PH.NS.CLG.NS": "PH.NS.CLG.BR",
        "PH.NS.FIX.NS": "PH.NS.FIX.SE",
        "PH.NS.CHB.SU": "PH.NS.CHB.SR",
        "PH.NS.CHB.PU": "PH.NS.CHB.PR"
      },
      "removed": [
        "PH.NS.ELEC.DT",
        "PH.NS.ELEC.WM"
      ],
      "scope": "portfolio-wide for the upgraded acceleration/drift-sensitive non-structural components",
      "effect": "falling-hazard INJURY reduction (neutralises non-collapse component injuries)",
      "note": "Non-structural equipment upgrade (thesis Table 6-3): brace ceilings (CLG.NS->CLG.BR), anchor/safety-wire fixtures (FIX.NS->FIX.SE, no casualty), reinforce CHB (SU/PU->SR/PR), remove desktop & wall-mounted electronics from the mitigated models. Applied to every building carrying these components -> NOT coverage-limited. This is the headline INJURY-reduction layer. Component-level fragility swap only \u2014 no new EDPs. Not tuned."
    }
  },
  "n_realizations": 1000,
  "n_buildings": 1021,
  "n_buildings_makati_MC": 96,
  "n_buildings_quezon_QC": 925,
  "total_replacement_cost_php": 30636997329.0,
  "whole_portfolio": {
    "loss_ratio": {
      "mean": 0.05753733065837781,
      "median": 0.04868721456444146,
      "std": 0.036483738734315686,
      "p05": 0.020025305015042814,
      "p10": 0.02445325351975061,
      "p16": 0.02940368918684115,
      "p50": 0.04868721456444146,
      "p84": 0.08445695376398203,
      "p90": 0.0976081504493925,
      "p95": 0.11857530738163387
    },
    "total_loss_php": {
      "mean": 1762771045.6985106,
      "median": 1491630062.567243,
      "std": 1117752206.1551635,
      "p05": 613515216.2582769,
      "p10": 749174262.7699592,
      "p16": 900840747.0799985,
      "p50": 1491630062.567243,
      "p84": 2587507466.882594,
      "p90": 2990420644.6066685,
      "p95": 3632791375.536471
    },
    "casualties": {
      "injuries": {
        "count": {
          "mean": 6682.670124639522,
          "median": 5041.357773800502,
          "std": 6660.886107827753,
          "p05": 994.3907828691321,
          "p10": 1527.6695544785719,
          "p16": 2091.8887215064033,
          "p50": 5041.357773800502,
          "p84": 10500.325613448973,
          "p90": 12752.60348438327,
          "p95": 17085.10870702499
        },
        "ratio": {
          "mean": 0.011927311955992814,
          "median": 0.008997877454430175,
          "std": 0.011888431574450329,
          "p05": 0.0017748009182308442,
          "p10": 0.002726603438759648,
          "p16": 0.003733628758156866,
          "p50": 0.008997877454430175,
          "p84": 0.018741110498531943,
          "p90": 0.02276100378627099,
          "p95": 0.030493712475704225
        }
      },
      "fatalities": {
        "count": {
          "mean": 479.7424476864395,
          "median": 388.2704857619803,
          "std": 383.0929816783402,
          "p05": 103.31790982951198,
          "p10": 140.05470190141244,
          "p16": 178.7144351350743,
          "p50": 388.2704857619803,
          "p84": 745.2821275527809,
          "p90": 878.7545996091161,
          "p95": 1087.9754878360986
        },
        "ratio": {
          "mean": 0.0008562502301273456,
          "median": 0.0006929899457273919,
          "std": 0.0006837490726621015,
          "p05": 0.00018440307813999708,
          "p10": 0.00024997135715595947,
          "p16": 0.00031897172524433955,
          "p50": 0.0006929899457273919,
          "p84": 0.0013301887216866847,
          "p90": 0.0015684120339348438,
          "p95": 0.0019418320524379618
        }
      },
      "population": 560283.0,
      "noncollapse_injury_fraction_median": 0.2443779989895535,
      "noncollapse_injury_fraction_mean": 0.2676668019071063,
      "noncollapse_fatality_fraction_median": 0.2702033427241504
    }
  },
  "makati_MC": {
    "loss_ratio": {
      "mean": 0.033567129635456903,
      "median": 0.02538248192924577,
      "std": 0.03314861428020504,
      "p05": 0.009203509624905393,
      "p10": 0.011700036580325014,
      "p16": 0.013940960203750068,
      "p50": 0.02538248192924577,
      "p84": 0.04775064005132954,
      "p90": 0.06331197032366614,
      "p95": 0.08493152917116897
    },
    "casualties": {
      "injuries": {
        "count": {
          "mean": 1202.7260440041484,
          "median": 583.0562371916906,
          "std": 2095.749901442277,
          "p05": 129.16756326835457,
          "p10": 185.98689414339395,
          "p16": 231.4700051268985,
          "p50": 583.0562371916906,
          "p84": 1783.570441146873,
          "p90": 2502.382945352715,
          "p95": 4061.947540930479
        },
        "ratio": {
          "mean": 0.01275844703989804,
          "median": 0.006185026224863853,
          "std": 0.02223159152470353,
          "p05": 0.0013702019037897355,
          "p10": 0.00197293801932124,
          "p16": 0.0024554201818932898,
          "p50": 0.006185026224863853,
          "p84": 0.018920010195789424,
          "p90": 0.026545130905734817,
          "p95": 0.04308890028461614
        }
      },
      "fatalities": {
        "count": {
          "mean": 147.68477515488775,
          "median": 117.30684927784293,
          "std": 120.87460753113778,
          "p05": 42.75474265178739,
          "p10": 57.80540795176328,
          "p16": 68.1780463825335,
          "p50": 117.30684927784293,
          "p84": 220.32292606231562,
          "p90": 259.7328048287295,
          "p95": 337.86709635008435
        },
        "ratio": {
          "mean": 0.0015666313969055336,
          "median": 0.0012443841483185665,
          "std": 0.0012822307177453647,
          "p05": 0.00045353979199723546,
          "p10": 0.000613196363086097,
          "p16": 0.0007232287006601692,
          "p50": 0.0012443841483185665,
          "p84": 0.0023371726236866373,
          "p90": 0.0027552302965845564,
          "p95": 0.0035840742593014076
        }
      },
      "population": 94269.0,
      "noncollapse_injury_fraction_median": 0.974254369090966,
      "noncollapse_injury_fraction_mean": 0.7261234618022545,
      "noncollapse_fatality_fraction_median": 0.9873816406673337
    }
  },
  "quezon_QC": {
    "loss_ratio": {
      "mean": 0.07022109435391824,
      "median": 0.06009931032487156,
      "std": 0.044402388763850255,
      "p05": 0.02399367336444865,
      "p10": 0.028609452154253034,
      "p16": 0.03436856376906538,
      "p50": 0.06009931032487156,
      "p84": 0.10288369064946608,
      "p90": 0.1181118926458939,
      "p95": 0.14977636845405856
    },
    "casualties": {
      "injuries": {
        "count": {
          "mean": 5479.944080635372,
          "median": 4258.441734590944,
          "std": 5416.169550228389,
          "p05": 773.3390191165588,
          "p10": 1194.3753070371795,
          "p16": 1572.6091267199286,
          "p50": 4258.441734590944,
          "p84": 8826.020284374921,
          "p90": 10422.069304971717,
          "p95": 13779.668934631552
        },
        "ratio": {
          "mean": 0.01175918337353679,
          "median": 0.009138012451537818,
          "std": 0.011622332269477717,
          "p05": 0.0016594759365953786,
          "p10": 0.0025629601407622504,
          "p16": 0.003374596314101998,
          "p50": 0.009138012451537818,
          "p84": 0.018939388697281456,
          "p90": 0.022364283701716513,
          "p95": 0.029569216664373933
        }
      },
      "fatalities": {
        "count": {
          "mean": 332.0576725315518,
          "median": 258.3390987284902,
          "std": 310.4220111847865,
          "p05": 39.57306796228075,
          "p10": 62.884264654760045,
          "p16": 87.99271639999998,
          "p50": 258.3390987284902,
          "p84": 543.9459388141428,
          "p90": 655.8965756201072,
          "p95": 876.6326670762546
        },
        "ratio": {
          "mean": 0.0007125487056859919,
          "median": 0.0005543590937793505,
          "std": 0.0006661216426647837,
          "p05": 8.491819550975025e-05,
          "p10": 0.0001349407199242084,
          "p16": 0.0001888198989729922,
          "p50": 0.0005543590937793505,
          "p84": 0.0011672308960978485,
          "p90": 0.0014074610969200651,
          "p95": 0.0018811294662311746
        }
      },
      "population": 466014.0,
      "noncollapse_injury_fraction_median": 0.18672456175361335,
      "noncollapse_injury_fraction_mean": 0.20291713163449343,
      "noncollapse_fatality_fraction_median": 0.02655801249787977
    }
  },
  "per_archetype_loss_ratio": {
    "C1-H (Hi)": {
      "n_buildings": 2,
      "mean_loss_ratio": 0.008700849602067517,
      "p16_loss_ratio": 0.0008637761946478143,
      "p84_loss_ratio": 0.011930358549132773,
      "collapse_rate": 0.002,
      "demolition_rate": 0.0005,
      "mean_injury_rate": 0.0013131575557110305,
      "mean_fatality_rate": 0.00034553137988036083
    },
    "C1-L (Mid/Hi)": {
      "n_buildings": 133,
      "mean_loss_ratio": 0.09843878984118588,
      "p16_loss_ratio": 0.05246504759856231,
      "p84_loss_ratio": 0.14136138313324006,
      "collapse_rate": 0.0008571428571428571,
      "demolition_rate": 0.0008496240601503759,
      "mean_injury_rate": 0.006477766916205407,
      "mean_fatality_rate": 3.830432009925558e-05
    },
    "C1-L (Pre/Lo)": {
      "n_buildings": 135,
      "mean_loss_ratio": 0.16786963009593484,
      "p16_loss_ratio": 0.05597538371006588,
      "p84_loss_ratio": 0.27300401310152056,
      "collapse_rate": 0.08271851851851852,
      "demolition_rate": 0.0383037037037037,
      "mean_injury_rate": 0.06504186911358699,
      "mean_fatality_rate": 0.005864110328925288
    },
    "C1-M (Hi)": {
      "n_buildings": 267,
      "mean_loss_ratio": 0.05425564985322413,
      "p16_loss_ratio": 0.02979677475069916,
      "p84_loss_ratio": 0.0771116206210152,
      "collapse_rate": 0.00034082397003745317,
      "demolition_rate": 0.0005543071161048689,
      "mean_injury_rate": 0.0027844144563817096,
      "mean_fatality_rate": 1.5728093212415857e-05
    },
    "C1-M (Mid)": {
      "n_buildings": 122,
      "mean_loss_ratio": 0.03445243912931033,
      "p16_loss_ratio": 0.016598231258898758,
      "p84_loss_ratio": 0.04712697194508555,
      "collapse_rate": 0.0009016393442622951,
      "demolition_rate": 0.0020901639344262295,
      "mean_injury_rate": 0.0028483502985707536,
      "mean_fatality_rate": 2.145959861591695e-05
    },
    "C1-M (Pre/Lo)": {
      "n_buildings": 71,
      "mean_loss_ratio": 0.03688820006336757,
      "p16_loss_ratio": 0.013853680760855415,
      "p84_loss_ratio": 0.05004364955595329,
      "collapse_rate": 0.009309859154929578,
      "demolition_rate": 4.225352112676056e-05,
      "mean_injury_rate": 0.010516723689854844,
      "mean_fatality_rate": 0.0002502734720509316
    },
    "CHB-L": {
      "n_buildings": 29,
      "mean_loss_ratio": 0.6689473464973505,
      "p16_loss_ratio": 0.4927795167059432,
      "p84_loss_ratio": 0.8515116617156068,
      "collapse_rate": 0.3478275862068966,
      "demolition_rate": 0.06741379310344828,
      "mean_injury_rate": 0.29198331607078576,
      "mean_fatality_rate": 0.022738369056068134
    },
    "CWS-L": {
      "n_buildings": 16,
      "mean_loss_ratio": 0.09948156777331062,
      "p16_loss_ratio": 0.03574970205911635,
      "p84_loss_ratio": 0.16640492372727086,
      "collapse_rate": 0.02025,
      "demolition_rate": 0.0,
      "mean_injury_rate": 0.01926376232630959,
      "mean_fatality_rate": 0.0008626903781355298
    },
    "N-L": {
      "n_buildings": 27,
      "mean_loss_ratio": 0.29936339650724775,
      "p16_loss_ratio": 0.08215723384740052,
      "p84_loss_ratio": 0.509529245049541,
      "collapse_rate": 0.265037037037037,
      "demolition_rate": 0.014925925925925926,
      "mean_injury_rate": 0.2502888512645775,
      "mean_fatality_rate": 0.006496573036649215
    },
    "PTC1-M (Hi)": {
      "n_buildings": 25,
      "mean_loss_ratio": 0.05128670427226662,
      "p16_loss_ratio": 0.028051718533966926,
      "p84_loss_ratio": 0.0714795628830774,
      "collapse_rate": 0.00164,
      "demolition_rate": 0.0,
      "mean_injury_rate": 0.010316283127244566,
      "mean_fatality_rate": 0.002121230659933289
    },
    "PTC1-M (Mid)": {
      "n_buildings": 39,
      "mean_loss_ratio": 0.023977941074184817,
      "p16_loss_ratio": 0.01256110779353978,
      "p84_loss_ratio": 0.03151429221748284,
      "collapse_rate": 0.0017948717948717949,
      "demolition_rate": 0.0001282051282051282,
      "mean_injury_rate": 0.0074858510073815615,
      "mean_fatality_rate": 0.0015434482430837818
    },
    "S1-M (Hi)": {
      "n_buildings": 73,
      "mean_loss_ratio": 0.05310450791336002,
      "p16_loss_ratio": 0.025379617370035922,
      "p84_loss_ratio": 0.07658873098835838,
      "collapse_rate": 0.0009452054794520548,
      "demolition_rate": 0.001547945205479452,
      "mean_injury_rate": 0.001881493845462647,
      "mean_fatality_rate": 0.00016900042714675925
    },
    "S3-L": {
      "n_buildings": 71,
      "mean_loss_ratio": 0.499169509387883,
      "p16_loss_ratio": 0.27445795471184137,
      "p84_loss_ratio": 0.739603354544577,
      "collapse_rate": 0.09401408450704225,
      "demolition_rate": 0.2573802816901408,
      "mean_injury_rate": 0.0814134585950972,
      "mean_fatality_rate": 0.004372738944508009
    },
    "W-L": {
      "n_buildings": 11,
      "mean_loss_ratio": 0.16252780069380607,
      "p16_loss_ratio": 0.0,
      "p84_loss_ratio": 0.3539499917428214,
      "collapse_rate": 0.11872727272727272,
      "demolition_rate": 0.045181818181818184,
      "mean_injury_rate": 0.1004631557397359,
      "mean_fatality_rate": 0.0040944008398950136
    }
  },
  "recovery_days_portfolio_mean": {
    "reoccupancy": {
      "mean": 421.13694218991674,
      "median": 422.5420090518623,
      "std": 31.716289382463273,
      "p05": 369.8926408641862,
      "p10": 384.41231349196295,
      "p16": 395.09398686161836,
      "p50": 422.5420090518623,
      "p84": 448.3289389409399,
      "p90": 456.4107627368765,
      "p95": 468.1349945510111
    },
    "functional_recovery": {
      "mean": 453.51490027725646,
      "median": 453.7532145016203,
      "std": 42.31414927398655,
      "p05": 384.47681527000293,
      "p10": 402.775014918404,
      "p16": 416.3835352171159,
      "p50": 453.7532145016203,
      "p84": 492.1016624231311,
      "p90": 504.6849579984267,
      "p95": 519.2953461043943
    },
    "full_recovery": {
      "mean": 462.9984126370406,
      "median": 460.08514883622183,
      "std": 57.58541863932438,
      "p05": 387.17187488744827,
      "p10": 405.2427012351961,
      "p16": 419.84119263603424,
      "p50": 460.08514883622183,
      "p84": 505.46352303689724,
      "p90": 519.7817997044237,
      "p95": 542.5801231916239
    }
  },
  "recovery_90pct_functional_days": {
    "weighting_basis": "building_count",
    "definition": "per realization: 90th percentile across buildings of the per-building recovery-milestone day (= time at which 90% of buildings, by count, have recovered); median + p90 across realizations. Thesis Portfolio_Analysis_2021.m line 214 (prctile(R_Func,90,1)). Collapsed+demolished buildings carry full replacement duration and drive the tail.",
    "whole_portfolio": {
      "reoccupancy": {
        "mean": 735.9051574695031,
        "median": 736.5857150877235,
        "p10": 697.031168169496,
        "p16": 704.8667921562238,
        "p84": 764.3711975291714,
        "p90": 774.8389484032336
      },
      "functional_recovery": {
        "mean": 790.1248268769327,
        "median": 787.6498369215889,
        "p10": 731.6273438322702,
        "p16": 745.120332801772,
        "p84": 836.9621741236949,
        "p90": 849.9052525533754
      },
      "full_recovery": {
        "mean": 804.184427511194,
        "median": 800.9254696124449,
        "p10": 736.9416597590479,
        "p16": 751.3254754426061,
        "p84": 857.2982806852207,
        "p90": 877.3747735942223
      }
    },
    "makati_MC": {
      "reoccupancy": {
        "mean": 804.0523151690778,
        "median": 792.8287561359369,
        "p10": 693.2972621448395,
        "p16": 713.7323499978116,
        "p84": 889.8267074177733,
        "p90": 920.2865724297726
      },
      "functional_recovery": {
        "mean": 948.6571377085916,
        "median": 945.6563906877258,
        "p10": 785.5304024799623,
        "p16": 819.1229545670816,
        "p84": 1074.8675221780006,
        "p90": 1106.5325935932526
      },
      "full_recovery": {
        "mean": 1022.7975582245258,
        "median": 1014.693991292017,
        "p10": 819.3743140968787,
        "p16": 866.1573798735882,
        "p84": 1175.43618249483,
        "p90": 1222.3146357933829
      }
    },
    "quezon_QC": {
      "reoccupancy": {
        "mean": 726.2595066184327,
        "median": 727.3509434103394,
        "p10": 688.6320268062362,
        "p16": 696.5731649908349,
        "p84": 757.2242616249765,
        "p90": 766.7625711694303
      },
      "functional_recovery": {
        "mean": 768.1530721078947,
        "median": 766.7851795479673,
        "p10": 714.2865785987026,
        "p16": 725.5556335218865,
        "p84": 811.2141268545217,
        "p90": 824.8047126158298
      },
      "full_recovery": {
        "mean": 774.667216202917,
        "median": 772.0398549715504,
        "p10": 714.5519775679461,
        "p16": 727.7340792877203,
        "p84": 822.0775106106488,
        "p90": 840.859631910788
      }
    },
    "thesis_targets_WVF73": {
      "makati_MC": {
        "functional_recovery_median_days": 970,
        "functional_recovery_p90_days": 1070
      },
      "quezon_QC": {
        "functional_recovery_median_days": 640,
        "functional_recovery_p90_days": 655
      },
      "source": "Jeswani 2021 \u00a77.4.4 p.181 + WVF_7_3_PA.mat PA_R[4] (QC Func-90% median=652, p90=661)",
      "provenance_confidence": "medium",
      "note": "Thesis used North American REDi impeding values (authors flagged for further review)."
    }
  },
  "recovery_curve_functional": {
    "days": [
      0.0,
      11.621848739495798,
      23.243697478991596,
      34.865546218487395,
      46.48739495798319,
      58.10924369747899,
      69.73109243697479,
      81.35294117647058,
      92.97478991596638,
      104.59663865546219,
      116.21848739495798,
      127.84033613445378,
      139.46218487394958,
      151.08403361344537,
      162.70588235294116,
      174.32773109243698,
      185.94957983193277,
      197.57142857142856,
      209.19327731092437,
      220.81512605042016,
      232.43697478991595,
      244.05882352941177,
      255.68067226890756,
      267.30252100840335,
      278.92436974789916,
      290.5462184873949,
      302.16806722689074,
      313.78991596638656,
      325.4117647058823,
      337.03361344537814,
      348.65546218487395,
      360.2773109243697,
      371.89915966386553,
      383.52100840336135,
      395.1428571428571,
      406.7647058823529,
      418.38655462184875,
      430.0084033613445,
      441.6302521008403,
      453.25210084033614,
      464.8739495798319,
      476.4957983193277,
      488.11764705882354,
      499.7394957983193,
      511.3613445378151,
      522.9831932773109,
      534.6050420168067,
      546.2268907563025,
      557.8487394957983,
      569.4705882352941,
      581.0924369747898,
      592.7142857142857,
      604.3361344537815,
      615.9579831932773,
      627.5798319327731,
      639.2016806722689,
      650.8235294117646,
      662.4453781512605,
      674.0672268907563,
      685.6890756302521,
      697.3109243697479,
      708.9327731092437,
      720.5546218487394,
      732.1764705882352,
      743.7983193277311,
      755.4201680672269,
      767.0420168067227,
      778.6638655462184,
      790.2857142857142,
      801.90756302521,
      813.5294117647059,
      825.1512605042017,
      836.7731092436975,
      848.3949579831932,
      860.016806722689,
      871.6386554621848,
      883.2605042016806,
      894.8823529411765,
      906.5042016806723,
      918.126050420168,
      929.7478991596638,
      941.3697478991596,
      952.9915966386554,
      964.6134453781513,
      976.2352941176471,
      987.8571428571428,
      999.4789915966386,
      1011.1008403361344,
      1022.7226890756302,
      1034.344537815126,
      1045.9663865546217,
      1057.5882352941176,
      1069.2100840336134,
      1080.8319327731092,
      1092.453781512605,
      1104.0756302521008,
      1115.6974789915967,
      1127.3193277310925,
      1138.9411764705883,
      1150.5630252100839,
      1162.1848739495797,
      1173.8067226890755,
      1185.4285714285713,
      1197.0504201680671,
      1208.672268907563,
      1220.2941176470588,
      1231.9159663865546,
      1243.5378151260504,
      1255.1596638655462,
      1266.781512605042,
      1278.4033613445379,
      1290.0252100840335,
      1301.6470588235293,
      1313.268907563025,
      1324.890756302521,
      1336.5126050420167,
      1348.1344537815125,
      1359.7563025210084,
      1371.3781512605042,
      1383.0
    ],
    "fraction_recovered": [
      0.05110871694417238,
      0.05110871694417238,
      0.05110871694417238,
      0.05110871694417238,
      0.05110871694417238,
      0.05110969637610186,
      0.05111753183153771,
      0.05117042115572968,
      0.05135749265426053,
      0.05186190009794319,
      0.05294613124387855,
      0.057601371204701275,
      0.06470910871694417,
      0.07192556317335945,
      0.08212536728697356,
      0.1000519098922625,
      0.11559353574926542,
      0.12985112634671891,
      0.14377277179236042,
      0.15970910871694416,
      0.17708521057786483,
      0.1956258570029383,
      0.215513222331048,
      0.23619588638589617,
      0.25744270323212537,
      0.27938491674828597,
      0.3012918707149853,
      0.3233790401567091,
      0.34556611165524,
      0.367820763956905,
      0.3896709108716944,
      0.4117502448579824,
      0.43328305582762,
      0.45444857982370224,
      0.4748315377081293,
      0.4948883447600392,
      0.521026444662096,
      0.5439314397649363,
      0.5683516160626837,
      0.5876082272282076,
      0.6051733594515181,
      0.6225063663075416,
      0.6387913809990206,
      0.6540910871694418,
      0.668945151811949,
      0.6833457394711068,
      0.696977473065622,
      0.7102389813907933,
      0.7227884427032322,
      0.7347668952007835,
      0.7468168462291871,
      0.7588305582761998,
      0.7732536728697356,
      0.785511263467189,
      0.7970822722820764,
      0.8079089128305583,
      0.8179333986287953,
      0.8269931439764936,
      0.8351224289911852,
      0.8429608227228208,
      0.8502037218413321,
      0.8572203721841332,
      0.8639089128305583,
      0.8701145935357493,
      0.8760910871694417,
      0.8822673849167483,
      0.8881204701273262,
      0.8935102840352596,
      0.8986082272282077,
      0.9033330068560235,
      0.9079167482859941,
      0.9121077375122429,
      0.9161929480901078,
      0.9201126346718903,
      0.9238579823702253,
      0.927460333006856,
      0.9307864838393731,
      0.9339843290891283,
      0.937024485798237,
      0.9398952007835455,
      0.9426718903036239,
      0.9452977473065622,
      0.9478305582761998,
      0.9501909892262488,
      0.9524250734573947,
      0.9545837414299706,
      0.9566229187071499,
      0.9585582761998042,
      0.9604368266405485,
      0.9621674828599412,
      0.963922624877571,
      0.9655044074436827,
      0.9670166503428012,
      0.9684662095984329,
      0.9698501469147894,
      0.9713065621939275,
      0.9726072477962782,
      0.9738609206660137,
      0.9749715964740451,
      0.9760881488736532,
      0.9771351616062683,
      0.9781292850146914,
      0.9790568070519099,
      0.9800274240940254,
      0.9808893241919686,
      0.9817316356513223,
      0.9825269343780607,
      0.9832546523016651,
      0.9840137120470127,
      0.9847384916748286,
      0.9853457394711067,
      0.9859588638589618,
      0.9865631733594515,
      0.9871488736532811,
      0.9876953966699314,
      0.9882007835455436,
      0.9887345739471107,
      0.9891909892262488,
      0.9896072477962782,
      0.9900117531831538
    ],
    "basis": "whole_portfolio_building_count_mean_over_realizations"
  },
  "collapse_rate_building_realizations": 0.03709598432908913,
  "demolition_rate_building_realizations": 0.026383937316356514,
  "extrapolated_fraction_above_edp_stripe": 0.0030950048971596475,
  "loss_source_decomposition": {
    "collapse_share_of_total_loss": 0.18149611568995508,
    "demolition_share_of_total_loss": 0.09541878295791327,
    "component_share_of_total_loss": 0.7230851013521317,
    "noncollapse_cell_loss_ratio_mean": 0.10338642043978863,
    "noncollapse_cell_loss_ratio_median": 0.040915051246367844
  },
  "model_caveats": {
    "loss_is_total_loss_dominated": false,
    "loss_is_collapse_dominated": false,
    "recovery_milestones_degenerate": false,
    "note": "Loss is decomposed 3 ways: collapse (Sa>collapse fragility -> replacement), residual-drift demolition (peak RIDR > the archetype's FEMA P-58 / Ramirez & Miranda 2012 demolition fragility, median = thesis Table 6-6 'Residual Drift Limit', beta=0.30 -> replacement), and component repair (Pelicun damage->loss on the real FEMA P-58 Table D-13 component inventory). The three shares sum to 1. Demolition closes the previously 'cold' pre-code / pseudo-EDP archetypes (e.g. C1-L (Pre/Lo)) that the 2021 Thesis demolished once residual drift passed ~1%; archetypes whose thesis residual-drift limit is 0.0% (residual drift NOT a governing criterion, e.g. CWS-L) get NO demolition by design. The three REDi recovery milestones (reoccupancy < functional < full) differentiate via the rc1/rc2/rc3 spread; total-loss (collapse OR demolition) cells take the full replacement duration. 'loss_is_total_loss_dominated' reports whether collapse+demolition exceeds 50% of total loss (a physical property of WVF Mw7.3, not an artefact). Real components + hazard (correct sigma) + collapse + residual-drift demolition + spatial correlation + per-building replacement are all live."
  },
  "provenance": {
    "hazard": "hazard.scenario_sa_field (Loth-Baker 2013 correlated; per-branch mean tau/phi single-event aleatory sigma)",
    "edp": "real multi-stripe PERFORM-3D EDPs via edp.demand_for_sa_field (per-realization Sa interpolation); residual-drift demolition demand via edp.median_residual_drift_for_sa_field (MEDIAN peak RIDR, capped at top calibrated stripe)",
    "loss": "Pelicun component damage->loss; collapse->replacement override AND residual-drift demolition override (FEMA P-58 2018a sec 7.6 / Ramirez & Miranda 2012: median-conditioned lognormal demolition fragility, median RIDR = thesis Table 6-6, beta=0.30; residual median NOT extrapolated above the calibrated stripe range) -> per-building replacement_cost_php / replacement_time_days",
    "recovery": "recovery.py REDi 3-milestone (PH-calibrated impeding factors)",
    "casualties": "casualties.py FEMA P-58 model: (a) non-collapse component injuries via the affected-area model (thesis Tables D-1/D-2 thetas + areas, casualty_consequences.json) on non-collapsed realizations; (b) collapse injuries/fatalities = collapse * population * P(TC) * {HAZUS-typology collapse fatality rate; injury = 1 - fatality} (thesis Ch 6.2.6.2). Scaled by per-building actual population. Demolition is NOT a casualty event. Collapse fatality rates inherit the loss-pipeline collapse-rate (which runs higher than the 2021 Thesis), so fatalities run high vs the thesis anchor \u2014 see docs/learnings/2026-06-27_casualties.md.",
    "generated_utc": "2026-06-27T23:20:50+00:00"
  }
}